sizeof/__init__.py
sizeof/sizeof.py
sizeof-0.6.0.dist-info/LICENSE
sizeof-0.6.0.dist-info/METADATA
sizeof-0.6.0.dist-info/WHEEL
sizeof-0.6.0.dist-info/top_level.txt
sizeof-0.6.0.dist-info/RECORD
